mflag/__init__.py
mflag/src/flag.py
mflag/src/lock/__init__.py
mflag-1.7.3.dist-info/LICENSE
mflag-1.7.3.dist-info/METADATA
mflag-1.7.3.dist-info/WHEEL
mflag-1.7.3.dist-info/top_level.txt
mflag-1.7.3.dist-info/RECORD
