Metadata-Version: 2.1
Name: mflag
Version: 1.7.3
Summary: put/remove flags for files and folders
Home-page: UNKNOWN
Author: Moses Dastmard
License: UNKNOWN
Platform: UNKNOWN
License-File: LICENSE
Requires-Dist: pandas
Requires-Dist: numpy
Requires-Dist: psutil
Requires-Dist: joblib
Requires-Dist: pathlib
